nondjango/__init__.py
nondjango-0.1.0.dist-info/LICENSE
nondjango-0.1.0.dist-info/WHEEL
nondjango-0.1.0.dist-info/METADATA
nondjango-0.1.0.dist-info/RECORD
